text_bridge/__init__.py
text_bridge/basic.py
text_bridge/config.py
text_bridge/embeddings.py
text_bridge/events.py
text_bridge/rate_limit.py
text_bridge/redis.py
text_bridge/search.py
text_bridge/templates.py
text_bridge/transformations.py
text_bridge-1.0.0.dist-info/METADATA
text_bridge-1.0.0.dist-info/WHEEL
text_bridge-1.0.0.dist-info/top_level.txt
text_bridge-1.0.0.dist-info/RECORD
