Metadata-Version: 2.1
Name: text-bridge
Version: 1.0.0
Summary: Allows to use prompt templates with OpenAI API
Home-page: UNKNOWN
Author: Damian Czapiewski
Author-email: damianczap@outlook.com
License: UNKNOWN
Platform: UNKNOWN
Requires-Python: >=3.6
Requires-Dist: setuptools (~=45.2.0)
Requires-Dist: Jinja2 (~=3.0.1)
Requires-Dist: openai[embeddings] (~=0.27.0)
Requires-Dist: transformers (~=4.28.1)
Requires-Dist: anthropic (~=0.2.9)
